god/__init__.py
god/__main__.py
god/cli.py
god_cli-1.0.1.dist-info/licenses/LICENSE
god_cli-1.0.1.dist-info/METADATA
god_cli-1.0.1.dist-info/WHEEL
god_cli-1.0.1.dist-info/entry_points.txt
god_cli-1.0.1.dist-info/top_level.txt
god_cli-1.0.1.dist-info/RECORD
