Metadata-Version: 2.4
Name: god-cli
Version: 1.0.1
Summary: Professional-grade global help indexer with BLUX integration
Author-email: "OuterVoid Team, Justadudeinspace" <outervoid.blux@gmail.com>
License-Expression: MIT
Project-URL: Homepage, https://github.com/Outer-Void/god
Project-URL: Documentation, https://github.com/Outer-Void/god/wiki
Project-URL: Repository, https://github.com/Outer-Void/god
Project-URL: Issues, https://github.com/Outer-Void/god/issues
Keywords: cli,help,documentation,indexer,blux,god
Classifier: Development Status :: 5 - Production/Stable
Classifier: Intended Audience :: Developers
Classifier: Intended Audience :: System Administrators
Classifier: Operating System :: OS Independent
Classifier: Programming Language :: Python :: 3
Classifier: Programming Language :: Python :: 3.8
Classifier: Programming Language :: Python :: 3.9
Classifier: Programming Language :: Python :: 3.10
Classifier: Programming Language :: Python :: 3.11
Classifier: Programming Language :: Python :: 3.12
Requires-Python: >=3.8
License-File: LICENSE
Requires-Dist: typer>=0.20.0
Requires-Dist: rich>=13.8.0
Requires-Dist: click>=8.1.7
Provides-Extra: dev
Requires-Dist: pytest>=8.2.0; extra == "dev"
Requires-Dist: pytest-cov>=4.1.0; extra == "dev"
Requires-Dist: pytest-timeout>=2.3.0; extra == "dev"
Requires-Dist: ruff>=0.4.0; extra == "dev"
Requires-Dist: mypy>=1.10.0; extra == "dev"
Requires-Dist: black>=24.4.0; extra == "dev"
Requires-Dist: isort>=5.13.2; extra == "dev"
Dynamic: license-file
